{
  "version": "1.6.27",
  "target": "v753",
  "time": "2019-02-24T12:59:37.435Z",
  "totals": {
    "objects": 1,
    "files": 2,
    "statements": 369,
    "tokens": 2180
  },
  "objects": [
    {
      "type": "PROG",
      "count": 1
    }
  ],
  "issues": [
    {
      "type": "check_variables",
      "count": 3
    }
  ],
  "objectOrientation": {
    "oo": 315,
    "non": 22
  },
  "methodLength": [
    0,
    3,
    4,
    1,
    0,
    0,
    3,
    0,
    1,
    0,
    0,
    1,
    1,
    1,
    0,
    0,
    0,
    1,
    1,
    0,
    1,
    2,
    0,
    0,
    0,
    0,
    0,
    0,
    0,
    0,
    0,
    0,
    0,
    1
  ],
  "statementTypes": [
    {
      "type": "Append",
      "count": 7
    },
    {
      "type": "Assert",
      "count": 5
    },
    {
      "type": "Call",
      "count": 20
    },
    {
      "type": "CallFunction",
      "count": 1
    },
    {
      "type": "Case",
      "count": 4
    },
    {
      "type": "Catch",
      "count": 1
    },
    {
      "type": "ClassDefinition",
      "count": 6
    },
    {
      "type": "ClassImplementation",
      "count": 6
    },
    {
      "type": "Clear",
      "count": 1
    },
    {
      "type": "Comment",
      "count": 32
    },
    {
      "type": "Concatenate",
      "count": 7
    },
    {
      "type": "Constant",
      "count": 1
    },
    {
      "type": "Continue",
      "count": 2
    },
    {
      "type": "CreateObject",
      "count": 1
    },
    {
      "type": "Data",
      "count": 28
    },
    {
      "type": "DeleteInternal",
      "count": 3
    },
    {
      "type": "Do",
      "count": 3
    },
    {
      "type": "Else",
      "count": 2
    },
    {
      "type": "ElseIf",
      "count": 1
    },
    {
      "type": "EndCase",
      "count": 4
    },
    {
      "type": "EndClass",
      "count": 12
    },
    {
      "type": "EndDo",
      "count": 3
    },
    {
      "type": "EndIf",
      "count": 15
    },
    {
      "type": "EndLoop",
      "count": 7
    },
    {
      "type": "EndMethod",
      "count": 21
    },
    {
      "type": "EndTry",
      "count": 1
    },
    {
      "type": "EndWhile",
      "count": 1
    },
    {
      "type": "Exit",
      "count": 1
    },
    {
      "type": "If",
      "count": 15
    },
    {
      "type": "Initialization",
      "count": 1
    },
    {
      "type": "Loop",
      "count": 7
    },
    {
      "type": "Method",
      "count": 21
    },
    {
      "type": "MethodDef",
      "count": 21
    },
    {
      "type": "Move",
      "count": 49
    },
    {
      "type": "Parameter",
      "count": 7
    },
    {
      "type": "Private",
      "count": 5
    },
    {
      "type": "Public",
      "count": 6
    },
    {
      "type": "ReadReport",
      "count": 1
    },
    {
      "type": "ReadTable",
      "count": 2
    },
    {
      "type": "Report",
      "count": 1
    },
    {
      "type": "Return",
      "count": 3
    },
    {
      "type": "Select",
      "count": 3
    },
    {
      "type": "SelectionScreen",
      "count": 6
    },
    {
      "type": "SelectOption",
      "count": 2
    },
    {
      "type": "Sort",
      "count": 1
    },
    {
      "type": "StartOfSelection",
      "count": 1
    },
    {
      "type": "Tables",
      "count": 2
    },
    {
      "type": "Translate",
      "count": 1
    },
    {
      "type": "Try",
      "count": 1
    },
    {
      "type": "Type",
      "count": 2
    },
    {
      "type": "TypeBegin",
      "count": 1
    },
    {
      "type": "TypeEnd",
      "count": 1
    },
    {
      "type": "When",
      "count": 8
    },
    {
      "type": "While",
      "count": 1
    },
    {
      "type": "Write",
      "count": 4
    }
  ],
  "statements": [
    {
      "type": "v700",
      "count": 353
    },
    {
      "type": "v702",
      "count": 354
    },
    {
      "type": "v740sp02",
      "count": 368
    },
    {
      "type": "v740sp05",
      "count": 369
    },
    {
      "type": "v740sp08",
      "count": 369
    },
    {
      "type": "v750",
      "count": 369
    },
    {
      "type": "v751",
      "count": 369
    },
    {
      "type": "v752",
      "count": 369
    },
    {
      "type": "v753",
      "count": 369
    },
    {
      "type": "Cloud",
      "count": 344
    }
  ]
}