{
  "version": "1.6.30",
  "target": "v753",
  "time": "2019-02-28T09:02:39.844Z",
  "totals": {
    "objects": 21,
    "files": 49,
    "statements": 859,
    "tokens": 4463
  },
  "objects": [
    {
      "type": "CLAS",
      "count": 15
    },
    {
      "type": "DEVC",
      "count": 1
    },
    {
      "type": "INTF",
      "count": 4
    },
    {
      "type": "PROG",
      "count": 1
    }
  ],
  "issues": [
    {
      "type": "check_variables",
      "count": 22
    },
    {
      "type": "class_attribute_names",
      "count": 9
    },
    {
      "type": "colon_missing_space",
      "count": 3
    },
    {
      "type": "definitions_top",
      "count": 1
    },
    {
      "type": "exporting",
      "count": 6
    },
    {
      "type": "indentation",
      "count": 2
    },
    {
      "type": "keywords_upper",
      "count": 5
    },
    {
      "type": "line_length",
      "count": 6
    },
    {
      "type": "line_only_punc",
      "count": 19
    },
    {
      "type": "local_class_naming",
      "count": 8
    },
    {
      "type": "local_variable_names",
      "count": 47
    },
    {
      "type": "method_parameter_names",
      "count": 24
    },
    {
      "type": "no_public_attributes",
      "count": 1
    },
    {
      "type": "superclass_final",
      "count": 1
    }
  ],
  "objectOrientation": {
    "oo": 702,
    "non": 9
  },
  "methodLength": [
    1,
    11,
    0,
    2,
    6,
    8,
    6,
    12,
    4,
    2,
    0,
    1,
    0,
    0,
    0,
    0,
    1,
    0,
    0,
    0,
    0,
    0,
    0,
    0,
    0,
    0,
    0,
    0,
    0,
    0,
    0,
    0,
    0,
    0,
    0,
    0,
    0,
    0,
    0,
    0,
    0,
    0,
    0,
    0,
    0,
    0,
    0,
    0,
    0,
    0,
    0,
    0,
    0,
    0,
    0,
    0,
    0,
    0,
    0,
    0,
    0,
    0,
    1
  ],
  "statementTypes": [
    {
      "type": "Assign",
      "count": 1
    },
    {
      "type": "Call",
      "count": 82
    },
    {
      "type": "Case",
      "count": 1
    },
    {
      "type": "Catch",
      "count": 8
    },
    {
      "type": "ClassDefinition",
      "count": 23
    },
    {
      "type": "ClassImplementation",
      "count": 23
    },
    {
      "type": "ClassOther",
      "count": 7
    },
    {
      "type": "Clear",
      "count": 7
    },
    {
      "type": "Comment",
      "count": 148
    },
    {
      "type": "Constant",
      "count": 5
    },
    {
      "type": "CreateData",
      "count": 4
    },
    {
      "type": "CreateObject",
      "count": 19
    },
    {
      "type": "Data",
      "count": 62
    },
    {
      "type": "Else",
      "count": 9
    },
    {
      "type": "EndCase",
      "count": 1
    },
    {
      "type": "EndClass",
      "count": 46
    },
    {
      "type": "EndIf",
      "count": 28
    },
    {
      "type": "EndInterface",
      "count": 4
    },
    {
      "type": "EndLoop",
      "count": 2
    },
    {
      "type": "EndMethod",
      "count": 55
    },
    {
      "type": "EndTry",
      "count": 8
    },
    {
      "type": "Exit",
      "count": 2
    },
    {
      "type": "FieldSymbol",
      "count": 3
    },
    {
      "type": "GetTime",
      "count": 1
    },
    {
      "type": "If",
      "count": 28
    },
    {
      "type": "InsertInternal",
      "count": 2
    },
    {
      "type": "Interface",
      "count": 4
    },
    {
      "type": "InterfaceDef",
      "count": 6
    },
    {
      "type": "Loop",
      "count": 2
    },
    {
      "type": "Method",
      "count": 55
    },
    {
      "type": "MethodDef",
      "count": 55
    },
    {
      "type": "Move",
      "count": 70
    },
    {
      "type": "Private",
      "count": 23
    },
    {
      "type": "Protected",
      "count": 15
    },
    {
      "type": "Public",
      "count": 17
    },
    {
      "type": "Raise",
      "count": 7
    },
    {
      "type": "ReadTable",
      "count": 2
    },
    {
      "type": "Report",
      "count": 1
    },
    {
      "type": "Return",
      "count": 1
    },
    {
      "type": "Translate",
      "count": 1
    },
    {
      "type": "Try",
      "count": 8
    },
    {
      "type": "Type",
      "count": 6
    },
    {
      "type": "TypeBegin",
      "count": 1
    },
    {
      "type": "TypeEnd",
      "count": 1
    },
    {
      "type": "When",
      "count": 2
    },
    {
      "type": "Write",
      "count": 3
    }
  ],
  "statements": [
    {
      "type": "v700",
      "count": 857
    },
    {
      "type": "v702",
      "count": 857
    },
    {
      "type": "v740sp02",
      "count": 859
    },
    {
      "type": "v740sp05",
      "count": 859
    },
    {
      "type": "v740sp08",
      "count": 859
    },
    {
      "type": "v750",
      "count": 859
    },
    {
      "type": "v751",
      "count": 859
    },
    {
      "type": "v752",
      "count": 859
    },
    {
      "type": "v753",
      "count": 859
    },
    {
      "type": "Cloud",
      "count": 848
    }
  ]
}